libreria_telegram/__init__.py
libreria_telegram/funciones.py
libreria_telegram-0.0.6.dist-info/METADATA
libreria_telegram-0.0.6.dist-info/WHEEL
libreria_telegram-0.0.6.dist-info/top_level.txt
libreria_telegram-0.0.6.dist-info/RECORD
