Metadata-Version: 2.1
Name: libreria-telegram
Version: 0.0.6
Summary: Librería para enviar mensajes a telegram
Home-page: https://github.com
Author: Oscar Becerril
Author-email: homerj.31@gmail.com
License: MIT
Requires-Dist: telethon
Requires-Dist: requests
